{
  "users": [
    {
      "id": "960bd490-ef69-4041-b35b-a564b6d15289",
      "username": "fer",
      "passHash": "$2a$10$eRIsL7UeLvzy3LcdjW3wCOKdN.tsPgGbMOqtwjsn2KFzf7Y7dQ9CO",
      "createdAt": 1757732877493,
      "lastLoginAt": null,
      "country": "Ecuador",
      "email": "fernando2000b@hotmail.com",
      "phone": "0983801298",
      "gender": "M"
    }
  ],
  "progress": {
    "960bd490-ef69-4041-b35b-a564b6d15289": {
      "money": 350,
      "bank": 0,
      "vehicle": null,
      "vehicles": [],
      "shops": [],
      "houses": [],
      "name": "fer",
      "avatar": "assets/avatar1.png",
      "likes": [
        "cine",
        "videojuegos",
        "ciclismo",
        "programación",
        "helado"
      ],
      "gender": "M",
      "age": 20,
      "initialRentPaid": true,
      "rentedHouseIdx": 0,
      "country": "Ecuador",
      "email": "fernando2000b@hotmail.com",
      "phone": "0983801298"
    },
    "ba25dd7e-1b5c-4d9b-bfa3-c9e73a7698c9": {
      "money": 350,
      "bank": 0,
      "vehicle": null,
      "vehicles": [],
      "shops": [],
      "houses": [],
      "name": null,
      "avatar": null,
      "likes": [],
      "gender": null,
      "age": null,
      "initialRentPaid": false,
      "rentedHouseIdx": null
    }
  },
  "government": {
    "funds": 0,
    "placed": []
  },
  "activityLog": [
    {
      "ts": 1757732877493,
      "type": "register",
      "userId": "960bd490-ef69-4041-b35b-a564b6d15289",
      "details": {
        "username": "fer"
      }
    },
    {
      "ts": 1757732882614,
      "type": "progress_update",
      "userId": "960bd490-ef69-4041-b35b-a564b6d15289",
      "details": {
        "keys": [
          "money",
          "bank",
          "vehicle",
          "vehicles",
          "shops",
          "houses",
          "name",
          "avatar",
          "likes",
          "gender",
          "age",
          "initialRentPaid",
          "rentedHouseIdx"
        ]
      }
    },
    {
      "ts": 1757732885118,
      "type": "progress_update",
      "userId": "960bd490-ef69-4041-b35b-a564b6d15289",
      "details": {
        "keys": [
          "money",
          "bank",
          "vehicle",
          "vehicles",
          "shops",
          "houses",
          "name",
          "avatar",
          "likes",
          "gender",
          "age",
          "initialRentPaid",
          "rentedHouseIdx",
          "country",
          "email",
          "phone"
        ]
      }
    },
    {
      "ts": 1757732894808,
      "type": "progress_update",
      "userId": "960bd490-ef69-4041-b35b-a564b6d15289",
      "details": {
        "keys": [
          "money",
          "bank",
          "vehicle",
          "vehicles",
          "shops",
          "houses",
          "name",
          "avatar",
          "likes",
          "gender",
          "age",
          "initialRentPaid",
          "rentedHouseIdx",
          "country",
          "email",
          "phone"
        ]
      }
    }
  ]
}